setup.py
PyJFuzz.egg-info/PKG-INFO
PyJFuzz.egg-info/SOURCES.txt
PyJFuzz.egg-info/dependency_links.txt
PyJFuzz.egg-info/entry_points.txt
PyJFuzz.egg-info/requires.txt
PyJFuzz.egg-info/top_level.txt
pyjfuzz/__init__.py
pyjfuzz/lib.py
pyjfuzz/pyjfuzz.py
pyjfuzz/core/__init__.py
pyjfuzz/core/pjf_configuration.py
pyjfuzz/core/pjf_decoretors.py
pyjfuzz/core/pjf_encoder.py
pyjfuzz/core/pjf_executor.py
pyjfuzz/core/pjf_external_fuzzer.py
pyjfuzz/core/pjf_factory.py
pyjfuzz/core/pjf_grammar.py
pyjfuzz/core/pjf_logger.py
pyjfuzz/core/pjf_mutation.py
pyjfuzz/core/pjf_mutators.py
pyjfuzz/core/pjf_process_monitor.py
pyjfuzz/core/pjf_server.py
pyjfuzz/core/pjf_testcase_server.py
pyjfuzz/core/pjf_updater.py
pyjfuzz/core/pjf_version.py
pyjfuzz/core/pjf_worker.py
pyjfuzz/core/certs/__init__.py
pyjfuzz/core/certs/server.pem
pyjfuzz/core/conf/__init__.py
pyjfuzz/core/conf/config.json
pyjfuzz/core/errors/__init__.py
pyjfuzz/core/patch/__init__.py
pyjfuzz/core/patch/socket.py
pyjfuzz/core/tools/__init__.py
pyjfuzz/core/tools/fuzzer.html
pyjfuzz/core/tools/jquery.flot.axislabels.js
pyjfuzz/core/tools/jquery.flot.min.js
pyjfuzz/core/tools/jquery.flot.time.js
pyjfuzz/core/tools/jquery.js
pyjfuzz/core/tools/bootstrap/css/bootstrap-theme.min.css
pyjfuzz/core/tools/bootstrap/css/bootstrap.min.css
pyjfuzz/core/tools/bootstrap/fonts/glyphicons-halflings-regular.eot
pyjfuzz/core/tools/bootstrap/fonts/glyphicons-halflings-regular.svg
pyjfuzz/core/tools/bootstrap/fonts/glyphicons-halflings-regular.ttf
pyjfuzz/core/tools/bootstrap/fonts/glyphicons-halflings-regular.woff
pyjfuzz/core/tools/bootstrap/fonts/glyphicons-halflings-regular.woff2
pyjfuzz/core/tools/bootstrap/js/bootstrap.js
pyjfuzz/core/tools/bootstrap/js/bootstrap.min.js
pyjfuzz/core/tools/bootstrap/js/npm.js
pyjfuzz/core/tools/font-awesome/css/font-awesome.min.css
pyjfuzz/core/tools/font-awesome/fonts/FontAwesome.otf
pyjfuzz/core/tools/font-awesome/fonts/fontawesome-webfont.eot
pyjfuzz/core/tools/font-awesome/fonts/fontawesome-webfont.svg
pyjfuzz/core/tools/font-awesome/fonts/fontawesome-webfont.ttf
pyjfuzz/core/tools/font-awesome/fonts/fontawesome-webfont.woff
